mayaff/__init__.py
mayaff/config.py
mayaff/file_resources.py
mayaff/flags.py
mayaff/mayaff_api.py
mayaff/output.py
mayaff/pyparser.py
mayaff/reformatter.py
mayaff/maya_configs/2018.json
mayaff/maya_configs/2020.json
mayaff/maya_configs/2022.json
mayaff/maya_configs/2023.json
mayaff/maya_configs/__init__.py
mayaff-1.1.0.dist-info/LICENSE
mayaff-1.1.0.dist-info/METADATA
mayaff-1.1.0.dist-info/WHEEL
mayaff-1.1.0.dist-info/entry_points.txt
mayaff-1.1.0.dist-info/top_level.txt
mayaff-1.1.0.dist-info/RECORD
